tests/__init__.py
tests/test_ahp_gaussian.py
tests/test_ahp_saaty.py
tests/test_config_manager.py
tests/test_decision_helper.py
ahp_gauss-0.1.4.dist-info/METADATA
ahp_gauss-0.1.4.dist-info/WHEEL
ahp_gauss-0.1.4.dist-info/entry_points.txt
ahp_gauss-0.1.4.dist-info/top_level.txt
ahp_gauss-0.1.4.dist-info/RECORD
