Metadata-Version: 2.1
Name: ahp-gauss
Version: 0.1.4
Summary: The AHP-Gaussian Decision Support Library is a extensible solution designed for multi-criteria decision-making (MCDM) leveraging both traditional and advanced AHP methodologies
Requires-Dist: pandas
Requires-Dist: matplotlib
Requires-Dist: pyyaml
Requires-Dist: pytest
